{
  "db_name": "PostgreSQL",
  "query": "\n            SELECT r.id, r.created_timestamp, r.receipt_number, r.receipt_date, r.document_id,\n                   COALESCE((SELECT SUM(ri.total) FROM receipt_item ri WHERE ri.receipt_id = r.id), 0) as \"total!\",\n                   c.id as \"contact_id?\", c.name as \"contact_name?\", c.first_name as \"contact_first_name?\"\n            FROM receipt r\n            LEFT JOIN contact c ON r.customer_contact_id = c.id\n            ORDER BY r.receipt_date DESC NULLS LAST, r.id DESC\n            ",
  "describe": {
    "columns": [
      {
        "ordinal": 0,
        "name": "id",
        "type_info": "Int4"
      },
      {
        "ordinal": 1,
        "name": "created_timestamp",
        "type_info": "Varchar"
      },
      {
        "ordinal": 2,
        "name": "receipt_number",
        "type_info": "Varchar"
      },
      {
        "ordinal": 3,
        "name": "receipt_date",
        "type_info": "Varchar"
      },
      {
        "ordinal": 4,
        "name": "document_id",
        "type_info": "Int4"
      },
      {
        "ordinal": 5,
        "name": "total!",
        "type_info": "Int8"
      },
      {
        "ordinal": 6,
        "name": "contact_id?",
        "type_info": "Int4"
      },
      {
        "ordinal": 7,
        "name": "contact_name?",
        "type_info": "Varchar"
      },
      {
        "ordinal": 8,
        "name": "contact_first_name?",
        "type_info": "Varchar"
      }
    ],
    "parameters": {
      "Left": []
    },
    "nullable": [
      false,
      true,
      true,
      true,
      true,
      null,
      false,
      false,
      true
    ]
  },
  "hash": "73e78e4d4bfe1c0eb3c4c50cd14a416107d33962cc343ec97280fd0745a91589"
}
